{
  "players": {
    "168fb922-274d-3073-b60c-a2ff41293a6d": {
      "uuid": "168fb922-274d-3073-b60c-a2ff41293a6d",
      "name": "PapetoOka",
      "deaths": 0,
      "killsPlayers": 0,
      "blocksBroken": 330,
      "blocksPlaced": 310,
      "mobsKilledTotal": 74
    },
    "892dce97-bb2b-36a7-aef4-63363cf65856": {
      "uuid": "892dce97-bb2b-36a7-aef4-63363cf65856",
      "name": "x_Alee",
      "deaths": 0,
      "killsPlayers": 0,
      "blocksBroken": 816,
      "blocksPlaced": 1,
      "mobsKilledTotal": 31
    },
    "b7052bed-f73b-3e2f-99f8-e7bb7096481c": {
      "uuid": "b7052bed-f73b-3e2f-99f8-e7bb7096481c",
      "name": "ElYuvy",
      "deaths": 0,
      "killsPlayers": 0,
      "blocksBroken": 181,
      "blocksPlaced": 34,
      "mobsKilledTotal": 6
    },
    "24a045d1-4311-3d3e-b8bf-a6accf2183b0": {
      "uuid": "24a045d1-4311-3d3e-b8bf-a6accf2183b0",
      "name": "Melendezqq",
      "deaths": 0,
      "killsPlayers": 0,
      "blocksBroken": 383,
      "blocksPlaced": 44,
      "mobsKilledTotal": 103
    }
  },
  "last_update": 1765243793561
}